pyutagger/__init__.py
pyutagger/downloader.py
pyutagger/hangul_util.py
pyutagger/utagger.py
pyutagger-1.0.1.1031.dist-info/LICENSE
pyutagger-1.0.1.1031.dist-info/METADATA
pyutagger-1.0.1.1031.dist-info/WHEEL
pyutagger-1.0.1.1031.dist-info/top_level.txt
pyutagger-1.0.1.1031.dist-info/RECORD
