Metadata-Version: 2.1
Name: pyutagger
Version: 1.0.1.1031
Summary: Python wrapper for UTagger
Home-page: http://klplab.ulsan.ac.kr
Author: Kim Wansu
Author-email: wantalia@gmail.com
License: MIT
Platform: UNKNOWN
Requires-Python: >=3.7
Requires-Dist: requests
Requires-Dist: tqdm
